python_logger_simple/__init__.py
python_logger_simple/logger.py
python_logger_simple-0.1.0.dist-info/METADATA
python_logger_simple-0.1.0.dist-info/WHEEL
python_logger_simple-0.1.0.dist-info/top_level.txt
python_logger_simple-0.1.0.dist-info/RECORD
