Metadata-Version: 2.4
Name: python-logger-simple
Version: 0.1.0
Summary: A simple Python logger module with configurable options.
Home-page: https://github.com/Cut0x/python-logger-simple
Author: Cut0x
Author-email: contact@valloic.dev
Classifier: Programming Language :: Python :: 3
Classifier: License :: OSI Approved :: MIT License
Classifier: Operating System :: OS Independent
Requires-Python: >=3.6
Requires-Dist: requests>=2.20
Dynamic: author
Dynamic: author-email
Dynamic: classifier
Dynamic: description
Dynamic: description-content-type
Dynamic: home-page
Dynamic: requires-dist
Dynamic: requires-python
Dynamic: summary
